{
    "version": "3.028",
    "description": "Sans serif font family for user interface environments.",
    "homepage": "https://adobe-fonts.github.io/source-sans",
    "license": "OFL-1.1",
    "url": "https://github.com/adobe-fonts/source-sans/releases/download/3.028R/source-sans-3v028R.zip",
    "hash": "1186d594ecb1336679a1d102bb6ddbe6041f0fd029482e53f02e46aa3ab011cf",
    "extract_dir": "TTF",
    "checkver": {
        "github": "https://github.com/adobe-fonts/source-sans"
    },
    "autoupdate": {
        "url": "https://github.com/adobe-fonts/source-sans/releases/download/$versionR/source-sans-$majorVersionv$minorVersionR.zip"
    },
    "installer": {
        "script": [
            "if (!(is_admin)) { error \"Admin rights are required, please run 'sudo scoop install $app'\"; exit 1 }",
            "Get-ChildItem $dir -filter '*.ttf' | ForEach-Object {",
            "  New-ItemProperty -Path 'HKLM:\\SOFTWARE\\Microsoft\\Windows NT\\CurrentVersion\\Fonts' -Name $_.Name.Replace($_.Extension, ' (TrueType)') -Value $_.Name -Force | Out-Null",
            "  Copy-Item $_.FullName -destination \"$env:windir\\Fonts\"",
            "}"
        ]
    },
    "uninstaller": {
        "script": [
            "if (!(is_admin)) { error \"Admin rights are required, please run 'sudo scoop install $app'\"; exit 1 }",
            "Get-ChildItem $dir -filter '*.ttf' | ForEach-Object {",
            "  Remove-ItemProperty -Path 'HKLM:\\SOFTWARE\\Microsoft\\Windows NT\\CurrentVersion\\Fonts' -Name $_.Name.Replace($_.Extension, ' (TrueType)') -Force -ErrorAction SilentlyContinue",
            "  Remove-Item \"$env:windir\\Fonts\\$($_.Name)\" -Force -ErrorAction SilentlyContinue",
            "}",
            "Write-Host \"The 'Source Sans' Font family has been uninstalled and will not be present after restarting your computer.\" -Foreground Magenta"
        ]
    }
}
